coin_count.py
coin_count-0.0.0.dist-info/METADATA
coin_count-0.0.0.dist-info/WHEEL
coin_count-0.0.0.dist-info/top_level.txt
coin_count-0.0.0.dist-info/RECORD
