Metadata-Version: 2.1
Name: coin-count
Version: 0.0.0
Summary: Application prints a change to be returned from a given sum amount in the number of coins
Home-page: UNKNOWN
Author: UNKNOWN
Author-email: UNKNOWN
License: UNKNOWN
Platform: UNKNOWN
